[
  {
    "pointcut": "be.unamur.game2048.models.Tile|mergeWith|(Lbe/unamur/game2048/models/Tile;)I|0|#result",
    "expected": [
      {
        "literalValue": "4",
        "typeName": "int"
      }
    ],
    "unexpected": [
      {
        "literalValue": "1",
        "typeName": "int"
      }
    ]
  },
  {
    "pointcut": "be.unamur.game2048.models.Tile|mergeWith|(Lbe/unamur/game2048/models/Tile;)I|0|#that|isMerged",
    "expected": [
      {
        "literalValue": "true",
        "typeName": "boolean"
      }
    ],
    "unexpected": [
      {
        "literalValue": "false",
        "typeName": "boolean"
      }
    ]
  },
  {
    "pointcut": "be.unamur.game2048.Test2048|testMergeWith()|4",
    "expected": [
      {
        "literalValue": "4",
        "typeName": "int"
      }
    ],
    "unexpected": [
      {
        "literalValue": "1",
        "typeName": "int"
      }
    ]
  },
  {
    "pointcut": "be.unamur.game2048.Test2048|testMergeWith()|5",
    "expected": [
      {
        "literalValue": "4",
        "typeName": "int"
      }
    ],
    "unexpected": [
      {
        "literalValue": "1",
        "typeName": "int"
      }
    ]
  },
  {
    "pointcut": "be.unamur.game2048.models.Tile|mergeWith|(Lbe/unamur/game2048/models/Tile;)I|0|#that|value",
    "expected": [
      {
        "literalValue": "4",
        "typeName": "java.lang.Integer"
      }
    ],
    "unexpected": [
      {
        "literalValue": "2",
        "typeName": "java.lang.Integer"
      }
    ]
  },
  {
    "pointcut": "be.unamur.game2048.Test2048|testMergeWithResultOnImpossibleMerging()|5",
    "expected": [
      {
        "literalValue": "-1",
        "typeName": "int"
      }
    ],
    "unexpected": [
      {
        "literalValue": "1",
        "typeName": "int"
      }
    ]
  },
  {
    "pointcut": "be.unamur.game2048.Test2048|testMergeWithResultOnImpossibleMerging()|4",
    "expected": [
      {
        "literalValue": "-1",
        "typeName": "int"
      }
    ],
    "unexpected": [
      {
        "literalValue": "1",
        "typeName": "int"
      }
    ]
  },
  {
    "pointcut": "be.unamur.game2048.models.Tile|mergeWith|(Lbe/unamur/game2048/models/Tile;)I|1|#result",
    "expected": [
      {
        "literalValue": "-1",
        "typeName": "int"
      }
    ],
    "unexpected": [
      {
        "literalValue": "1",
        "typeName": "int"
      }
    ]
  }
]